line_solver/__init__.py
line_solver/__main__.py
line_solver/_backend.py
line_solver/api/__init__.py
line_solver/api/aoi/__init__.py
line_solver/api/aoi/analytical.py
line_solver/api/aoi/bufferless.py
line_solver/api/aoi/conversion.py
line_solver/api/aoi/lst.py
line_solver/api/aoi/singlebuffer.py
line_solver/api/aoi/validation.py
line_solver/api/butools/__init__.py
line_solver/api/butools/dmap/__init__.py
line_solver/api/butools/dmap/basedmap.py
line_solver/api/butools/dmap/check.py
line_solver/api/butools/dmap/dmapfromdrap.py
line_solver/api/butools/dmap/matching.py
line_solver/api/butools/dmap/misc.py
line_solver/api/butools/dph/__init__.py
line_solver/api/butools/dph/acyclic.py
line_solver/api/butools/dph/appie.py
line_solver/api/butools/dph/basedph.py
line_solver/api/butools/dph/canonical.py
line_solver/api/butools/dph/check.py
line_solver/api/butools/dph/dphfrommg.py
line_solver/api/butools/dph/misc.py
line_solver/api/butools/fitting/__init__.py
line_solver/api/butools/fitting/dist.py
line_solver/api/butools/fitting/gfit.py
line_solver/api/butools/fitting/logli.py
line_solver/api/butools/fitting/spemfit.py
line_solver/api/butools/mam/__init__.py
line_solver/api/butools/mam/fluid.py
line_solver/api/butools/mam/mg1gm1.py
line_solver/api/butools/mam/qbd.py
line_solver/api/butools/mam/smc_jit.py
line_solver/api/butools/map/__init__.py
line_solver/api/butools/map/basemap.py
line_solver/api/butools/map/check.py
line_solver/api/butools/map/mapfromrap.py
line_solver/api/butools/map/matching.py
line_solver/api/butools/map/minimalrep.py
line_solver/api/butools/map/misc.py
line_solver/api/butools/mc/__init__.py
line_solver/api/butools/mc/check.py
line_solver/api/butools/mc/stst.py
line_solver/api/butools/moments/__init__.py
line_solver/api/butools/moments/check.py
line_solver/api/butools/moments/conv.py
line_solver/api/butools/mvph/__init__.py
line_solver/api/butools/mvph/mvph_jit.py
line_solver/api/butools/ph/__init__.py
line_solver/api/butools/ph/appie.py
line_solver-3.0.3.3.dist-info/AUTHORS
line_solver-3.0.3.3.dist-info/LICENSE
line_solver-3.0.3.3.dist-info/METADATA
line_solver-3.0.3.3.dist-info/WHEEL
line_solver-3.0.3.3.dist-info/entry_points.txt
line_solver-3.0.3.3.dist-info/RECORD
