Metadata-Version: 2.3
Name: line-solver
Version: 3.0.3.3
Summary: Open source queueing theory solvers
License: BSD-3
Author: Giuliano Casale
Author-email: g.casale@imperial.ac.uk
Requires-Python: >=3.11
Classifier: License :: Other/Proprietary License
Classifier: Programming Language :: Python :: 3
Classifier: Programming Language :: Python :: 3.11
Classifier: Programming Language :: Python :: 3.12
Classifier: Programming Language :: Python :: 3.13
Provides-Extra: gpu
Provides-Extra: native
Requires-Dist: enum-tools (>=0.13.0,<0.14.0)
Requires-Dist: matplotlib (>=3.10.6,<4.0.0)
Requires-Dist: numba (>=0.57.0) ; extra == "native"
Requires-Dist: numpy (>=2.3.3,<3.0.0)
Requires-Dist: pandas (>=2.3.2,<3.0.0)
Requires-Dist: scipy (>=1.16.2,<2.0.0)
Requires-Dist: simpy (>=4.0.0,<5.0.0)
Requires-Dist: torch (>=2.0.0) ; extra == "native" or extra == "gpu"
Requires-Dist: websockets (>=12.0,<13.0)
Project-URL: Homepage, https://line-solver.sourceforge.net
